.travis.yml
LICENSE
MANIFEST.in
README.md
pyproject.toml
requirements.txt
setup.py
./repack/utils/cutils.c
demo/PF_Schwenke_TiO.dat
demo/repack_HCN.cfg
demo/repack_TiO.cfg
demo/wget_exomol_hcn.txt
lbl_repack.egg-info/PKG-INFO
lbl_repack.egg-info/SOURCES.txt
lbl_repack.egg-info/dependency_links.txt
lbl_repack.egg-info/entry_points.txt
lbl_repack.egg-info/requires.txt
lbl_repack.egg-info/top_level.txt
repack/__init__.py
repack/__main__.py
repack/isotopes.dat
repack/pack.py
repack/version.py
repack/constants/__init__.py
repack/constants/constants.py
repack/utils/__init__.py
repack/utils/cutils.c
repack/utils/utilities.py
tests/exomol_repack_missing1.cfg
tests/exomol_repack_missing2.cfg
tests/exomol_repack_single.cfg
tests/exomol_repack_single_chunks.cfg
tests/exomol_repack_single_unzip.cfg
tests/exomol_repack_two_files.cfg
tests/exomol_repack_two_isotopes.cfg
tests/exomol_repack_two_two.cfg
tests/exomol_sort.cfg
tests/hitemp_repack_single_chunks.cfg
tests/hitemp_repack_single_unzip.cfg
tests/hitemp_repack_single_zip.cfg
tests/hitemp_repack_two.cfg
tests/test_exomol.py
tests/test_hitemp.py
tests/test_sorting.py
tests/test_utils.py