Metadata-Version: 2.1
Name: lbl-repack
Version: 1.4.5
Summary: A line-transition data compression package
Author-email: Patricio Cubillos <patricio.cubillos@oeaw.ac.at>
License: MIT License
Project-URL: Homepage, https://github.com/pcubillos/repack
Requires-Python: >=3.9
License-File: LICENSE
Requires-Dist: numpy>=2.0
Requires-Dist: scipy>=1.13.0
